ChanlunJingjie/README.md
ChanlunJingjie/__init__.py
ChanlunJingjie/__main__.py
ChanlunJingjie/file.epub
ChanlunJingjie/index.html
ChanlunJingjie/css/__init__.py
ChanlunJingjie/css/annotations.css
ChanlunJingjie/css/main.css
ChanlunJingjie/css/normalize.css
ChanlunJingjie/css/popup.css
ChanlunJingjie/font/__init__.py
ChanlunJingjie/font/fontello.eot
ChanlunJingjie/font/fontello.svg
ChanlunJingjie/font/fontello.ttf
ChanlunJingjie/font/fontello.woff
ChanlunJingjie/img/__init__.py
ChanlunJingjie/img/annotator-glyph-sprite.png
ChanlunJingjie/img/annotator-icon-sprite.png
ChanlunJingjie/img/apple-touch-icon.png
ChanlunJingjie/img/cancelfullscreen.png
ChanlunJingjie/img/close.png
ChanlunJingjie/img/fullscreen.png
ChanlunJingjie/img/loader.gif
ChanlunJingjie/img/menu-icon.png
ChanlunJingjie/img/save.png
ChanlunJingjie/img/saved.png
ChanlunJingjie/img/settings-s.png
ChanlunJingjie/img/settings.png
ChanlunJingjie/img/star.png
ChanlunJingjie/js/__init__.py
ChanlunJingjie/js/epub.js
ChanlunJingjie/js/epub.min.js
ChanlunJingjie/js/epub.min.map
ChanlunJingjie/js/hooks.min.js
ChanlunJingjie/js/hooks.min.map
ChanlunJingjie/js/reader.js
ChanlunJingjie/js/reader.js.map
ChanlunJingjie/js/reader.min.js
ChanlunJingjie/js/reader.min.map
ChanlunJingjie/js/hooks/__init__.py
ChanlunJingjie/js/hooks/extensions/__init__.py
ChanlunJingjie/js/hooks/extensions/highlight.js
ChanlunJingjie/js/libs/__init__.py
ChanlunJingjie/js/libs/jquery.min.js
ChanlunJingjie/js/libs/localforage.min.js
ChanlunJingjie/js/libs/screenfull.js
ChanlunJingjie/js/libs/screenfull.min.js
ChanlunJingjie/js/libs/zip.min.js
ChanlunJingjie/js/plugins/__init__.py
ChanlunJingjie/js/plugins/hypothesis.js
ChanlunJingjie/js/plugins/search.js
chanlun_jingjie-2022.10.15.0.dist-info/METADATA
chanlun_jingjie-2022.10.15.0.dist-info/WHEEL
chanlun_jingjie-2022.10.15.0.dist-info/entry_points.txt
chanlun_jingjie-2022.10.15.0.dist-info/top_level.txt
chanlun_jingjie-2022.10.15.0.dist-info/RECORD
